{"paths":{"0":["img/button/back_y",2],"1":["img/button/btn_ok",2],"2":["img/button/music_h",2],"3":["img/man/shang",2],"4":["img/button/start_b",2],"5":["img/button/share_y",2],"6":["img/man_beat",2],"7":["img/button/btn_ok2",2],"8":["img/female",2],"9":["img/bomb2",2],"10":["sound/bg",4],"11":["img/button/replay_y",2],"12":["img/dialog",2],"13":["img/button/about_b",2],"14":["sound/da2",4],"15":["img/quantou-m",2],"16":["img/bg_r",2],"17":["img/male",2],"18":["img/button/info_g",2],"19":["img/button/replay_b",2],"20":["img/woman/shang",2],"21":["img/bg-idx",2],"22":["img/man/normal",2],"23":["img/quan",2],"24":["img/logo",2],"25":["img/bg_con3",2],"26":["img/button/music_b",2],"27":["sound/click",4],"28":["sound/boom",4],"29":["img/qiub-m",2],"30":["img/button/back_b",2],"31":["splash/default_image",2],"32":["sound/countdown",4],"33":["img/boom",2],"34":["img/man/jing",2],"35":["font/fz",0],"36":["img/num/texture",2],"37":["img/woman/normal",2],"38":["img/button/about_g",2],"39":["img/qiub",2],"40":["sound/quan2",4],"41":["sound/bang",4],"42":["img/button/btn_no",2],"43":["sound/a",4],"44":["sound/quan",4],"45":["img/woman/result",2],"46":["img/bg2",2],"47":["img/bg",2],"48":["img/button/home_g",2],"49":["img/bomb",2],"50":["img/controlboximg",2],"51":["img/man/beat_r",2],"52":["img/start",2],"53":["img/button/share_b",2],"54":["img/button/musice_y",2],"55":["img/man/beat_l",2],"56":["img/man",2],"57":["img/button/replay_g",2],"58":["img/button/share_g",2],"59":["img/button/info_y",2],"60":["img/star/texture",2],"61":["img/aboutbox",2],"62":["sound/countdown2",4],"63":["img/woman/beat_l",2],"64":["img/dialog2",2],"65":["img/man/result",2],"66":["img/woman/beat_r",2],"67":["img/button/start_y",2],"68":["img/button/start_g",2],"69":["img/button/home_y",2],"70":["img/button/back_g",2],"71":["img/about",2],"72":["img/button/about_y",2],"73":["img/button/music_g",2],"74":["img/woman/jing",2],"75":["img/quantou",2],"76":["sound/quan3",4],"77":["img/aboutbox2",2],"78":["img/qiubang",2],"79":["img/title",2],"80":["img/man/beat_r",1,1],"81":["img/button/music_h",1,1],"82":["img/button/replay_b",1,1],"83":["img/man/beat_l",1,1],"84":["img/button/back_y",1,1],"85":["img/quan",1,1],"86":["img/woman/beat_r",1,1],"87":["img/button/share_y",1,1],"88":["img/button/music_g",1,1],"89":["img/star/texture",3],"90":["img/button/btn_no",1,1],"91":["img/button/share_b",1,1],"92":["img/man/normal",1,1],"93":["img/button/btn_ok",1,1],"94":["img/woman/result",1,1],"95":["img/logo",1,1],"96":["img/female",1,1],"97":["img/num/texture",3],"98":["img/button/info_g",1,1],"99":["img/woman/beat_l",1,1],"100":["splash/default_image",1,1],"101":["img/title",1,1],"102":["img/button/back_b",1,1],"103":["img/boom",1,1],"104":["img/button/info_y",1,1],"105":["img/button/back_g",1,1],"106":["img/quantou-m",1,1],"107":["img/qiub",1,1],"108":["img/button/share_g",1,1],"109":["img/man_beat",1,1],"110":["img/qiub-m",1,1],"111":["img/bg_r",1,1],"112":["img/button/home_g",1,1],"113":["img/button/music_b",1,1],"114":["img/button/start_b",1,1],"115":["img/bg-idx",1,1],"116":["img/dialog2",1,1],"117":["img/button/home_y",1,1],"118":["img/button/btn_ok2",1,1],"119":["img/bomb",1,1],"120":["img/button/start_g",1,1],"121":["img/button/start_y",1,1],"122":["img/man/result",1,1],"123":["img/aboutbox",1,1],"124":["img/button/about_g",1,1],"125":["img/man",1,1],"126":["img/man/shang",1,1],"127":["img/start",1,1],"128":["img/woman/normal",1,1],"129":["img/bg2",1,1],"130":["img/male",1,1],"131":["img/controlboximg",1,1],"132":["img/button/about_y",1,1],"133":["img/button/about_b",1,1],"134":["img/about",1,1],"135":["img/button/musice_y",1,1],"136":["img/woman/shang",1,1],"137":["img/woman/jing",1,1],"138":["img/button/replay_g",1,1],"139":["img/bg",1,1],"140":["img/dialog",1,1],"141":["img/aboutbox2",1,1],"142":["img/bomb2",1,1],"143":["img/qiubang",1,1],"144":["img/man/jing",1,1],"145":["img/bg_con3",1,1],"146":["img/quantou",1,1],"147":["img/button/replay_y",1,1]},"types":["cc.TTFFont","cc.SpriteFrame","cc.Texture2D","cc.SpriteAtlas","cc.AudioClip"],"uuids":["02k9LViwFOpLtPTsjzhDiA","0a7vb2WDtKbqnX8Lac/BlJ","0euh+V3BRLa6PWdFqIG3T2","11SNwv3UxDharw67aMLH2V","14icrOfgxOaoN9FZc53uNS","15X05MfbBNeIyEi7FrCJ6q","15iQ5qLiNMIr43WLz+Qf7a","17FEFKvpBByLiUp4VDLSyx","21PC6PbNlMaJK+ubFrsUzQ","21PgziiFlGeJJnHTMoKi+Z","23JrhIVEJBfqaWvVEgbHHG","23d7nLQlBGFY6t5C+a2TfE","24Q9ktGcpNhaviSWQhYukL","265M2MRIpIZ7m65vMXvM0f","2bAA9rsYhF241KPkhB2AOc","2cHNnpHUdN9rSPOT1NcTII","35QWibKqFLOJ+ff9RBbZJ1","3bRSjHndZGYIP5U2DGwcw4","3beTH7Ix9OUJmVJncn5onL","3fXRe1vJxNvIKMtrJ08U50","42JG51jU1P5a5/4YFTODss","43mNOc/85BgrvI9tEJAVKm","4eBcygSNRGO4cClxfgBPNx","4f6oC0djFMAbyACxs/lQ4c","5853puJFhCxbuh95gWrKki","5aTaHvs01N5LaLJiq7dWxI","629r9fhZZFfbgGYnC2QlqR","635GwpGM9IrI9DN1+o90sA","67vxgww1BCs7cOKgWuXHLD","6blvQqhx9MGo9u6ZOzi61O","6eLLaJGcxDYoZoJZpx55jU","700elcSK5FYarhome0LY/b","73+KaYDnJPnp1vuhsE2pkr","76XUncdPZA1ZUHUWCZp5IK","76xbJUDSVEC7TdX6GhrIzi","77SPAvA99CooGCLrYpZeFl","77SnMHb65Dl68AO+xczrGy","7fLoxby4xPKZFOAnbaJXmz","81JEaLRnFKK7GMXRxBkM3H","81a4rTMtVIN57XDQyir6Ez","83Q0gDgJpAFoHznGlieq/+","86+peiFqJIa4imf4ypK3H5","87IHs0nMJF5J+ExCLmp3r+","88TqpaEZJEmK+wwNPdOtva","8bNODS9LBGK6ht3ifrK4SR","8bR4bvR6xDoK9Tv1MJ9BfG","8eSSX/T71ENJAb3jXaVkf/","8f8rg4yMZBVqjBq7FjYD3A","90gwZyWp5MEq/nDOSk7ket","9dqAH9NhZA/YrjuM7lPFuS","9f6mwCGvdBtJpJKL0xHKc2","a3ssEreMZBf7bM0Mh7ahDo","a411SFh1lAjrzLxrMkDPih","b0OvRIxTBAELlr9YMVop20","b2wEOFbyxDToYBnxz8LbQ9","b5UOGKEi9NNKBQdyGIbH+x","b6aPNnd+ZKYK1yvTKQQGFF","beZvfDbUZH9plfJOP/tOAN","c4kpp12A5Ivb//18h8wM6H","c5HUR/ITtDPLHePoTHV98o","c5QKwwjtNCqZ4XAYa2WN/Z","c7NktNvcJIwamsNI85uYp/","c94+3OyjFCDaFrzfPkeXOy","ccnEI4bu5KR4VhD1UIoaId","d5gvcehYdHjpDnzitZoFSX","d5tz4uH9ZJepYETexp3bKM","d6Hrs8LMRC3YFt6gENiyLX","d6w6gBuoxOOa2SlHOBUH50","d8mJv0Vk9GcqFQ3DtMUwZk","dbiQOR7ElMQq3E/1mQUrP7","dbyWWmeFVDk4lGHLBcRbSH","dchB2SE2xGJ6Zmr9vbawDH","dfURYbIf5DOaTzqf0HhtPA","e8UUPAj8pENaky7wSRP4Yy","ecDOgzqAlImoyK+nqkU2+4","efILK5ij5NZbNgKH617hQG","f7GEm976dKIZvfg45ks1zv","f8N9uHupdAZ4L6y43DStY/","ffnE6l4ylDr4nqV/iITVhU","ffyiJl9spL5bKpRSGscrvF","0248r7cs5CxqV4ndLbwFuh","0d6Yr324BDspd6BRYqX7u1","11tb1WJh1Kl7VoFeTf623E","14dt6OJOZEkbBhNLOzBs/h","14iT9yL21DzKm0evMr5Fox","15Wzf061ZOxLseHPuy5T8X","16mVfyGt9DY5rFK/e+VmJ0","1bvPKHuMBDULyYRHn1DOL7","1eYda2VD1J/qCG69Za9kcv","211/Ff0j9KJJUSJicj0hCB","2273AqFkJNGp55JnuLX8VE","25Zs9mEb5H37+xX0njZRFl","2cDjx/z41NerngL3n17jJ+","311ZrGIldPv6loE/OFQAUR","40595cNXREk4mL4dDg3HsG","41eZR0v3VECJBh9mWLuEnS","4111939WlI0p9QRJ+C9lx1","418H8gqnBIe7CHEp0Fsx4Q","4a3Qd9j8pBrpBo3eQtm+DL","4cQD7X6ONHaLGDAjGi6C9J","5881d8i9NFR6ASQLaGX8MI","5aH2472GRNn4K5hUtiRxoy","5adRPp3/xPAIu9FA0XTN2u","5foC2luSVJ8oWhFhXNeYI+","67CijWecVBDrA3amj5qaV7","68QBoQRgJPxry8DqGSzaxF","692+oVvtFOsrXpOYMKlJ8u","6aU6tYVeRPkrElafx8QGoU","6ck+302KFCWIFjlnYoJ8Kf","6clko+t31MXrBPWOoBn4ne","6cooTeZLRD8K4XAVk/o4rz","6dfZZ//JBNz7gQ1nEEmtMl","71nUun+GhPHoD5w9jekfwq","75xHXhILdF0pxr5pHI+wC9","7fGQRD1UBDeqPJI9YBu/qU","80K0jVsgdM4rWT+bV3znjr","81FjIU/xpDhpZnPxQzOoR7","82Sglyw5FDVIoiuVyHuQo2","88DQ5NGZdPxJtX0HMUvdT5","8cvBlDGihOzIPWCanGnN5Q","8dC2Cx6rVFGYrzwwLneutd","8eMIcsih9OcaXg2i2ZWpXZ","8e7jpMBttMo45LE8yGxzPJ","90S/ZrL9pP7ahPV6p9PMsa","91TrIE8+FJXpkEDP3+TMEG","9bEmPcvfNCWoXa59KEvZpS","a0hvrLLn1NhYCUlyro0Pr7","a4ev77y7VKc4LfRKmdYDp+","afkRuuAKVA0ZRyeCIsIXan","b1UIzhdMZDK4Rp3aBj+x9Z","b2NOKDdSBLK5UJI9KwLm2h","b7vKiv1k1PerbM+QPvrxKR","b8+0VUUDJPLbh5Wsi82GI5","b9rvxOwptISI9aaJp3zS19","bcV2EeZpBNjbDzJI0e6Bgj","c7f89YXCVM1oFAOkr64X22","c9OqHQr9RHCbR864pNvHe6","c9lX6f2mZIfpD6LrwdpWBO","d04Fv22jxCQbsVz+RtCVtX","d7NUgo+RhEjbptZOfJ+P3E","d800LqD85J37lGh+dc1IK6","dfAf5tk2hJ6LWwEG0cVgKd","e4gfQL1IpFj7d7ziqhW5nM","e5gl/wpcxHxbK2WaTl4o0B","ecG/EYSzxL2pPM7l4J31C3","ee9pN1NWRFA608IXriYFwH","f3jWZS5V5JDbsSLXf1kvGA","f9PhPFraFNdZWJKqpMu9Ua","00AHfb+HxCH6E3zq4ZkAlD","0cBgGLcpdKhayteugtGh4s","380ST6s/NLbYdPjGb+BLgy","40CusPJQxLm6DZuK7kJWW7","41GYS+HyRAur4NUVyt7gqj","42CHVWbLRPQrifnpScNosC","49sqC5071PI6tDWEBUAvwg","62wbNXNUBMiI1JkEHTIsq2","63QDGy0sJDjpzuoKgE7SxJ","67dMwzMlFG5ZVuMAny7kMA","70WipbWI9Mh5+2V2aooGIL","74CcxFud9LUqq1dmcZyYEw","76ld7gwpVLw6W7dBRrOEF/","8evaqczYJK55NsPQDu0Ne1","9b8jIxzaxL8L7sDsa9rz+X","a2yaSe6ZJNLLrQo0MgNkoY","a3wy91KJhJFaZZ7E47qrS6","abAAyoXPlNsJ5dhAUAJHzv","ab/C00IaRCqq4SlYqcL9GK","acaz8w5LxPr7UgCg/c/9mw","f3r32lb7VHLq/O8mYACan0","f7OSX06MBHhLiWYe21Yr6a"],"scenes":{},"redirect":[],"deps":[],"packs":{"06d858f77":[148,149,150,97,153,156,157,159,161,162,167],"0d711b076":[89,151,152,154,155,158,160,163,164,165,166,168,169],"0e77c1ba0":[0,1,2,3,4,5,6,7,8,9,11,12,13,15,16,17,18,19,20,21,22,23,24,25,26,29,30,31,33,34,36,37,38,39,42,45,46,47,48,49,50,51,52,53,54,55,56,57,58,59,60,61,63,64,65,66,67,68,69,70,71,72,73,74,75,77,78,79]},"name":"resources","importBase":"import","nativeBase":"native","debug":false,"isZip":false,"encrypted":false,"versions":{"import":[80,"64158","06d858f77","96eff","0d711b076","4a915",81,"13769","0e77c1ba0","28dad",82,"bbe9a",83,"27cf7",84,"94115",85,"6cc8e",86,"407fc",87,"9073f",88,"5fcc7",90,"41742",10,"ae9c0",91,"bb0ee",14,"e6f7c",92,"8bb89",93,"d1ac2",94,"67dfa",95,"62a86",96,"10e3c",98,"c5b8d",99,"c1fb2",100,"e601d",101,"b19ca",102,"7f871",103,"65bf5",27,"71030",104,"26bf9",28,"838d9",105,"0e261",106,"ee767",107,"73fe4",108,"29adc",109,"617f5",110,"dbbf5",111,"021df",112,"3c6fc",32,"f262a",113,"8bcd5",35,"51713",114,"5a2b8",115,"97246",116,"c21f6",117,"9aad2",40,"f870c",41,"aa918",118,"34c1b",43,"90888",44,"2ae4e",119,"f3bbd",120,"1e3d5",121,"e6f9b",122,"0ab4b",123,"f4cf2",124,"03993",125,"a3425",126,"4d8ba",127,"4979f",128,"2f210",129,"6ebc7",130,"46d77",131,"a7de8",132,"ec22a",133,"8fb36",134,"89b1f",135,"f5077",136,"84c70",137,"1c58c",62,"8703e",138,"e2185",139,"1ba0b",140,"e89d8",141,"e53d6",142,"8e74d",143,"2e5bc",144,"53ef8",145,"1ba5f",146,"d5c9d",76,"e5fb7",147,"99677"],"native":[0,"ad93c",1,"d01ac",2,"2620b",3,"7d3b4",4,"e6e81",5,"cb72a",6,"2d9d4",7,"c79bf",8,"d5c63",9,"cff34",10,"400b5",11,"b0c06",12,"5dd2b",13,"31ee0",14,"e2523",15,"98dfc",16,"2c191",17,"6ae95",18,"afc34",19,"74b08",20,"8fb96",21,"20faf",22,"07a31",23,"cf79e",24,"87058",25,"55fec",26,"3d54a",27,"80f41",28,"a2b1c",29,"5a62a",30,"f23ff",31,"9a145",32,"ee6b6",33,"5214f",34,"cd297",35,"72b10",36,"63949",37,"965e7",38,"5f4c9",39,"c4853",40,"73730",41,"e0edd",42,"dd978",43,"bc23e",44,"cf714",45,"599ef",46,"6dd91",47,"f5899",48,"db743",49,"d39b8",50,"6a376",51,"4d12b",52,"182f2",53,"282aa",54,"15231",55,"b5f85",56,"266d2",57,"5b381",58,"67e4b",59,"3eab5",60,"9128a",61,"352c7",62,"11f48",63,"1d534",64,"ff569",65,"836ed",66,"aaab8",67,"e7093",68,"d2352",69,"244d8",70,"f9b74",71,"cb8b2",72,"2a66b",73,"82f40",74,"941e3",75,"91410",76,"972f9",77,"debcf",78,"ad1a4",79,"08479"]}}